{"nodes": [{"id": "c_users_glpen_documents_evilbounce_src_theme_src_routes_menu_altmanager_altmanager_store_ts", "label": "altmanager_store.ts", "file_type": "code", "source_file": "C:\\Users\\glpen\\Documents\\EVILBOUNCE\\src-theme\\src\\routes\\menu\\altmanager\\altmanager_store.ts", "source_location": "L1"}, {"id": "altmanager_altmanager_store_isloggingin", "label": "isLoggingIn", "file_type": "code", "source_file": "C:\\Users\\glpen\\Documents\\EVILBOUNCE\\src-theme\\src\\routes\\menu\\altmanager\\altmanager_store.ts", "source_location": "L4"}], "edges": [{"source": "c_users_glpen_documents_evilbounce_src_theme_src_routes_menu_altmanager_altmanager_store_ts", "target": "store", "relation": "imports_from", "context": "import", "confidence": "EXTRACTED", "source_file": "C:\\Users\\glpen\\Documents\\EVILBOUNCE\\src-theme\\src\\routes\\menu\\altmanager\\altmanager_store.ts", "source_location": "L1", "weight": 1.0}, {"source": "c_users_glpen_documents_evilbounce_src_theme_src_routes_menu_altmanager_altmanager_store_ts", "target": "c_users_glpen_documents_evilbounce_src_theme_src_integration_ws_ts", "relation": "imports_from", "context": "import", "confidence": "EXTRACTED", "source_file": "C:\\Users\\glpen\\Documents\\EVILBOUNCE\\src-theme\\src\\routes\\menu\\altmanager\\altmanager_store.ts", "source_location": "L2", "weight": 1.0}, {"source": "c_users_glpen_documents_evilbounce_src_theme_src_routes_menu_altmanager_altmanager_store_ts", "target": "integration_ws_listenalways", "relation": "imports", "context": "import", "confidence": "EXTRACTED", "source_file": "C:\\Users\\glpen\\Documents\\EVILBOUNCE\\src-theme\\src\\routes\\menu\\altmanager\\altmanager_store.ts", "source_location": "L2", "weight": 1.0}, {"source": "c_users_glpen_documents_evilbounce_src_theme_src_routes_menu_altmanager_altmanager_store_ts", "target": "altmanager_altmanager_store_isloggingin", "relation": "contains", "confidence": "EXTRACTED", "source_file": "C:\\Users\\glpen\\Documents\\EVILBOUNCE\\src-theme\\src\\routes\\menu\\altmanager\\altmanager_store.ts", "source_location": "L4", "weight": 1.0}], "raw_calls": []}