{"nodes": [{"id": "c_users_glpen_documents_evilbounce_src_main_java_net_ccbluex_liquidbounce_interfaces_memberretriever_java", "label": "MemberRetriever.java", "file_type": "code", "source_file": "C:\\Users\\glpen\\Documents\\EVILBOUNCE\\src\\main\\java\\net\\ccbluex\\liquidbounce\\interfaces\\MemberRetriever.java", "source_location": "L1"}, {"id": "interfaces_memberretriever_memberretriever", "label": "MemberRetriever", "file_type": "code", "source_file": "C:\\Users\\glpen\\Documents\\EVILBOUNCE\\src\\main\\java\\net\\ccbluex\\liquidbounce\\interfaces\\MemberRetriever.java", "source_location": "L24"}, {"id": "interfaces_memberretriever_memberretriever_getmember", "label": ".getMember()", "file_type": "code", "source_file": "C:\\Users\\glpen\\Documents\\EVILBOUNCE\\src\\main\\java\\net\\ccbluex\\liquidbounce\\interfaces\\MemberRetriever.java", "source_location": "L26"}], "edges": [{"source": "c_users_glpen_documents_evilbounce_src_main_java_net_ccbluex_liquidbounce_interfaces_memberretriever_java", "target": "member", "relation": "imports", "context": "import", "confidence": "EXTRACTED", "source_file": "C:\\Users\\glpen\\Documents\\EVILBOUNCE\\src\\main\\java\\net\\ccbluex\\liquidbounce\\interfaces\\MemberRetriever.java", "source_location": "L22", "weight": 1.0}, {"source": "c_users_glpen_documents_evilbounce_src_main_java_net_ccbluex_liquidbounce_interfaces_memberretriever_java", "target": "interfaces_memberretriever_memberretriever", "relation": "contains", "confidence": "EXTRACTED", "source_file": "C:\\Users\\glpen\\Documents\\EVILBOUNCE\\src\\main\\java\\net\\ccbluex\\liquidbounce\\interfaces\\MemberRetriever.java", "source_location": "L24", "weight": 1.0}, {"source": "interfaces_memberretriever_memberretriever", "target": "interfaces_memberretriever_memberretriever_getmember", "relation": "method", "confidence": "EXTRACTED", "source_file": "C:\\Users\\glpen\\Documents\\EVILBOUNCE\\src\\main\\java\\net\\ccbluex\\liquidbounce\\interfaces\\MemberRetriever.java", "source_location": "L26", "weight": 1.0}], "raw_calls": []}